rtl/alu/mul.sv
module mul #(
    parameter D_WIDTH = 32
) (
    input  logic [D_WIDTH-1:0] rd1, 
    input  logic [D_WIDTH-1:0] rd2, 
    input  logic [1:0] mul_ctrl,     // func3[1:0]

    output logic [D_WIDTH-1:0] result
);

logic [D_WIDTH*2-1:0] full_result;

always_comb begin
    case (mul_ctrl)
    2'b00: begin    ///MUL
        full_result = rd1*rd2;
        result = full_result[D_WIDTH-1:0];
    end
    2'b01: begin    ///MULH
        full_result = $signed(rd1)*$signed(rd2); 
        result = full_result[D_WIDTH*2-1:D_WIDTH];
    end
    2'b10: begin    ///MULHSU
        /// had to explicitly make rd1 64 bits because Multiplying 32-bit signed × 32-bit unsigned in Verilator 
        ///may produce a 32-bit intermediate result, resulting in garbage going into the top 32 bits 
        full_result = $signed({{32{rd1[31]}}, rd1}) * $unsigned(rd2);
        result = full_result[D_WIDTH*2-1:D_WIDTH];
    end
    2'b11: begin    ///MULHU
        full_result = $unsigned(rd1)*$unsigned(rd2); 
        result = full_result[D_WIDTH*2-1:D_WIDTH];
    end
    endcase
end
    
endmodule

rtl/alu/mul.vcd
$version Generated by VerilatedVcd $end
$date Sat Dec  6 20:55:22 2025 $end
$timescale 1ps $end

 $scope module TOP $end
  $var wire  2 % mul_ctrl [1:0] $end
  $var wire 32 # rd1 [31:0] $end
  $var wire 32 $ rd2 [31:0] $end
  $var wire 32 & result [31:0] $end
  $scope module mul $end
   $var wire 32 ) D_WIDTH [31:0] $end
   $var wire 64 ' full_result [63:0] $end
   $var wire  2 % mul_ctrl [1:0] $end
   $var wire 32 # rd1 [31:0] $end
   $var wire 32 $ rd2 [31:0] $end
   $var wire 32 & result [31:0] $end
  $upscope $end
 $upscope $end
$enddefinitions $end


#0
b00000000000000000000000000001010 #
b00000000000000000000000000000011 $
b00 %
b00000000000000000000000000011110 &
b0000000000000000000000000000000000000000000000000000000000011110 '
b00000000000000000000000000100000 )
#1
b11111111111111111111111111111011 #
b00000000000000000000000000000110 $
b11111111111111111111111111100010 &
b0000000000000000000000000000010111111111111111111111111111100010 '
#2
b01111111111111111111111111111111 #
b00000000000000000000000000000010 $
b11111111111111111111111111111110 &
b0000000000000000000000000000000011111111111111111111111111111110 '
#3
b00000000000000000000000000001010 #
b00000000000000000000000000000011 $
b01 %
b00000000000000000000000000000000 &
b0000000000000000000000000000000000000000000000000000000000011110 '
#4
b11111111111111111111111111111011 #
b00000000000000000000000000000110 $
b11111111111111111111111111111111 &
b1111111111111111111111111111111111111111111111111111111111100010 '
#5
b01111111111111111111111111111111 #
b00000000000000000000000000000010 $
b00000000000000000000000000000000 &
b0000000000000000000000000000000011111111111111111111111111111110 '
#6
b00000000000000000000000000001010 #
b00000000000000000000000000000011 $
b10 %
b0000000000000000000000000000000000000000000000000000000000011110 '
#7
b11111111111111111111111111111011 #
b00000000000000000000000000000110 $
b11111111111111111111111111111111 &
b1111111111111111111111111111111111111111111111111111111111100010 '
#8
b01111111111111111111111111111111 #
b00000000000000000000000000000010 $
b00000000000000000000000000000000 &
b0000000000000000000000000000000011111111111111111111111111111110 '
#9
b00000000000000000000000000001010 #
b00000000000000000000000000000011 $
b11 %
b0000000000000000000000000000000000000000000000000000000000011110 '
#10
b11111111111111111111111111111111 #
b00000000000000000000000000000010 $
b00000000000000000000000000000001 &
b0000000000000000000000000000000111111111111111111111111111111110 '
#11
b01111111111111111111111111111111 #
b00000000000000000000000000000000 &
b0000000000000000000000000000000011111111111111111111111111111110 '
